{
  "pose": {
    "prompts": [
      "a women sitting on bed",
      "looking up, smile",
      "leaning forward",
      "arched back",
      "dynamic pose",
      "(look back:1.3)",
      "sit in a chair",
      "girl sitting",
      "hand between legs, room",
      "bed room, smile",
      "selfie, smile",
      "Hands on Hips",
      "left hand on hips",
      "woman with left hand in pockets",
      "(Looking Over Shoulder:1.3), smile",
      "tilting head",
      "Arching the back"
    ],
    "use max prompts": 1,
    "use min prompts": 1
  },
  "Face": {
    "prompts": [
      "smile",
      "smile",
      "smile",
      "smile",
      "smile",
      "Half-smile",
      "Half-smile",
      "Half-smile",
      "Mournful",
      "",
      "",
      ""
    ],
    "use max prompts": 1,
    "use min prompts": 1
  }
}
