{
  "Base Positive Prompt": {
    "prompts": [
      "(masterpiece, best quality, high quality, highres, 8k, detailed), (RPG icon:1.3), (game asset:1.2), (fantasy style:1.2), (pixel perfect:1.1), (clean background:1.2), (centered composition:1.1)"
    ],
    "use_max_prompts": 1,
    "use_min_prompts": 1
  },
  "Monster Type": {
    "prompts": [
      "dragon",
      "goblin",
      "orc",
      "troll",
      "ogre",
      "giant",
      "demon",
      "devil",
      "angel",
      "elemental",
      "golem",
      "undead",
      "skeleton",
      "zombie",
      "ghost",
      "wraith",
      "vampire",
      "werewolf",
      "minotaur",
      "centaur",
      "harpy",
      "mermaid",
      "naga",
      "chimera",
      "griffin",
      "phoenix",
      "unicorn",
      "pegasus",
      "basilisk",
      "cockatrice",
      "hydra",
      "kraken",
      "leviathan",
      "behemoth",
      "slime",
      "spider",
      "scorpion",
      "insect",
      "plant monster",
      "treant",
      "mushroom creature",
      "fairy",
      "pixie",
      "gnome",
      "dwarf",
      "elf",
      "lizardman",
      "birdman",
      "fishman",
      "ratman"
    ],
    "use_max_prompts": 1,
    "use_min_prompts": 1
  },
  "Size": {
    "prompts": [
      "tiny",
      "small",
      "medium",
      "large",
      "huge",
      "gigantic",
      "colossal"
    ],
    "use_max_prompts": 1,
    "use_min_prompts": 1
  },
  "Difficulty": {
    "prompts": [
      "common enemy",
      "elite enemy",
      "mini-boss",
      "boss",
      "raid boss",
      "world boss",
      "secret boss",
      "final boss"
    ],
    "use_max_prompts": 1,
    "use_min_prompts": 0
  },
  "Habitat": {
    "prompts": [
      "forest",
      "jungle",
      "swamp",
      "desert",
      "mountain",
      "cave",
      "dungeon",
      "ruins",
      "castle",
      "village",
      "city",
      "plains",
      "hills",
      "tundra",
      "arctic",
      "volcanic",
      "ocean",
      "river",
      "lake",
      "island",
      "sky",
      "floating island",
      "abyss",
      "underworld",
      "hell",
      "heaven",
      "astral plane",
      "ethereal plane",
      "shadow realm",
      "dream world",
      "alternate dimension"
    ],
    "use_max_prompts": 1,
    "use_min_prompts": 0
  }
}